{
  "يزد‏": {
    "ابرکوه": [
      {
        "آدرس": "خيابان نظاميه روبروي مصلي",
        "تلفن": "32821573",
        "نام مرکز": "آزمايشگاه پارسيان ابركوه",
        "نوع تخصص": "آزمايشگاه تشخيصي پزشکي",
        "کد رایانه": 29875
      },
      {
        "آدرس": "ابرکوه_خيابان ميربرهان",
        "تلفن": "32829203",
        "نام مرکز": "آزمايشگاه رازي ( دكتر زهرا اعيان ) - يزد آنلاين",
        "نوع تخصص": "آزمايشگاه تشخيصي پزشکي",
        "کد رایانه": 10419
      },
      {
        "آدرس": "ابرکوه - خيابان شهيد بهشتي - جنب کوچه 11 شهيد بهشتي",
        "تلفن": "32830009",
        "نام مرکز": "داروخانه دكتر سميرا غلامي - ابركوه آنلاين",
        "نوع تخصص": "داروخانه",
        "کد رایانه": 27429
      },
      {
        "آدرس": "بلوار امام خميني",
        "تلفن": "32821141",
        "نام مرکز": "داروخانه دكتر عادل  - ابركوه آنلاين",
        "نوع تخصص": "داروخانه",
        "کد رایانه": 26415
      },
      {
        "آدرس": "يزد - ابرکوه خيابان شهيد صدوقي",
        "تلفن": "32821060",
        "نام مرکز": "داروخانه دكتربهاره قديريان - ابركوه آنلاين",
        "نوع تخصص": "داروخانه",
        "کد رایانه": 10412
      },
      {
        "آدرس": "خيابان شهيد صدوقي بعد از پمپ بنزين خيابان ميربرهان",
        "تلفن": "32825985",
        "نام مرکز": "درمانگاه دندانپزشكي ايرانيان (دكتر زهرا زارعزاده )- ابركوه آنلاين",
        "نوع تخصص": "دندانپزشک- عمومي",
        "کد رایانه": 23631
      },
      {
        "آدرس": "ابرکوه - خيابان شهيد صدوقي",
        "تلفن": "32825356",
        "نام مرکز": "دكتر سيد كمال الدين صحافي - ابركوه آنلاين",
        "نوع تخصص": "عمومي",
        "کد رایانه": 26416
      },
      {
        "آدرس": "ابرکوه_ميدان حج وزيارت",
        "تلفن": "035328434",
        "نام مرکز": "فيزيوتراپي طلوع ( زهرا پور زارع زاده ) - ابركوه آنلاين",
        "نوع تخصص": "فيزيوتراپيست",
        "کد رایانه": 10400
      },
      {
        "آدرس": "ابرکوه -",
        "تلفن": "03532827662",
        "نام مرکز": "فيزيوتراپي نوين (سوسن كيهاني ) - ابركوه آنلاين",
        "نوع تخصص": "فيزيوتراپيست",
        "کد رایانه": 10418
      }
    ],
    "اردکان": [
      {
        "آدرس": "خ امام -",
        "تلفن": "32322686",
        "نام مرکز": "آزمايشگاه پاتوبيولوژي كيان تشخيص اردكان (دكترمحمدعلي پوردهقان) -  آنلاين",
        "نوع تخصص": "آزمايشگاه تشخيصي پزشکي",
        "کد رایانه": 10181
      },
      {
        "آدرس": "ابتداي خيابان صدر آباد ساختمان کاج",
        "تلفن": "03532241515",
        "نام مرکز": "آزمايشگاه صدر (آنلاين)يزد",
        "نوع تخصص": "آزمايشگاه تشخيصي پزشکي",
        "کد رایانه": 30499
      },
      {
        "آدرس": "اردکان - جنب ميدان آزادي",
        "تلفن": "32222114",
        "نام مرکز": "بيمارستان قائم - ضيائي_اردكان آنلاين",
        "نوع تخصص": "بستري",
        "کد رایانه": 3571
      },
      {
        "آدرس": "اردکان - ميدان آزادي - داخل بيمارستان ضيايي اردکان",
        "تلفن": "32248192",
        "نام مرکز": "داروخانه شبانه روزي رازي (دكتر مصطفي شجاع الديني اردكاني ) -يزدآنلاين",
        "نوع تخصص": "داروخانه",
        "کد رایانه": 11688
      },
      {
        "آدرس": "اردکان - بلوار شهيد بهشتي - کوچه 80",
        "تلفن": "32227208",
        "نام مرکز": "مركز فيزيوتراپي حيدري ( مجيد حيدري بفروئي ) - اردكان-آنلاين",
        "نوع تخصص": "موسسه فيزيوتراپي",
        "کد رایانه": 18308
      },
      {
        "آدرس": "خيابان شهيد مصطفي خميني کلينيک فرهنگيان",
        "تلفن": "32228230",
        "نام مرکز": "مطب دكتر محمود خيرخواه",
        "نوع تخصص": "عمومي",
        "کد رایانه": 30173
      }
    ],
    "بافق": [
      {
        "آدرس": "يزد بافق",
        "تلفن": "32424040",
        "نام مرکز": "بيمارستان ولي عصر بافق-آنلاين",
        "نوع تخصص": "بستري",
        "کد رایانه": 3570
      },
      {
        "آدرس": "بافق-ميدان اما زاده - داخل پارکينگ شهرداري",
        "تلفن": "32427500",
        "نام مرکز": "داروخانه دكتر حمزه - بافق- آنلاين",
        "نوع تخصص": "داروخانه",
        "کد رایانه": 21199
      },
      {
        "آدرس": "بافق - بلوار وحشي بافقي",
        "تلفن": "32420022",
        "نام مرکز": "داروخانه دكتر زينلي (دكتر طيبه زينلي) - يزد-",
        "نوع تخصص": "داروخانه",
        "کد رایانه": 10376
      },
      {
        "آدرس": "بافق - خيابان عدالت -جنب کلينيک وليعصر",
        "تلفن": "32438283",
        "نام مرکز": "داروخانه دكترقلي زاده - بافق - آنلاين",
        "نوع تخصص": "داروخانه",
        "کد رایانه": 21245
      }
    ],
    "بهاباد": [
      {
        "آدرس": "بهاباد-ابتداي ميدان پرستار",
        "تلفن": "32471504",
        "نام مرکز": "بيمارستان حكيم - بهاباد- آنلاين",
        "نوع تخصص": "بيمارستان",
        "کد رایانه": 21059
      },
      {
        "آدرس": "بهاباد - جنب بيمارستان حکيم",
        "نام مرکز": "داروخانه دكترمحمدي حاجي آبادي-بهاباد-آنلاين",
        "نوع تخصص": "داروخانه",
        "کد رایانه": 21437
      }
    ],
    "تفت": [
      {
        "آدرس": "تفت - خيابان ساحلي - ساختمان پزشک خانواده",
        "تلفن": "32626543",
        "نام مرکز": "آزمايشگاه ابن سينا (دكتر فرجام فرد ) - تفت",
        "نوع تخصص": "آزمايشگاه",
        "کد رایانه": 11512
      },
      {
        "آدرس": "تفت جاده ساحلي",
        "تلفن": "32633001",
        "نام مرکز": "بيمارستان شهيد   بهشتي_تفت-آنلاين",
        "نوع تخصص": "بستري",
        "کد رایانه": 3568
      },
      {
        "آدرس": "تفت - خيابان امام خميني",
        "تلفن": "32627200",
        "نام مرکز": "داروخانه دكتر صفي ( دكتر محمد مهدي صفي ) - تفت آنلاين",
        "نوع تخصص": "داروخانه",
        "کد رایانه": 23571
      },
      {
        "آدرس": "تفت - خيابان شهيد بهشتي - جنب بيمارستان شهيد بهشتي",
        "تلفن": "035522114",
        "نام مرکز": "داروخانه شبانه روزي دكتر حسيني بيوكي (سيدمحمود حسيني بيوكي ) - تفت آنلاين",
        "نوع تخصص": "داروخانه",
        "کد رایانه": 11905
      },
      {
        "آدرس": "تفت - مجتمع تجاري پوپک طلائي",
        "تلفن": "32626452",
        "نام مرکز": "عينك سازي آريا ( نازيلا جليلي تفتي ) - يزد",
        "نوع تخصص": "اپتومتريست - عينک سازي",
        "کد رایانه": 10361
      }
    ],
    "خاتم": [
      {
        "آدرس": "هرات - خيابان امام -نبش خيابان طالقاني",
        "تلفن": "32575236",
        "نام مرکز": "داروخانه دكتر برفي ( حميد برفي ) - هرات آنلاين",
        "نوع تخصص": "داروخانه",
        "کد رایانه": 23573
      }
    ],
    "شاهديه": [
      {
        "آدرس": "شاهديه - گرد فرامرز - بلوار وحدت جنوبي",
        "تلفن": "35215650",
        "نام مرکز": "درمانگاه امام حسين ( دكترامين سلطاني ) - يزد آنلاين",
        "نوع تخصص": "کلينيک و درمانگاه",
        "کد رایانه": 25032
      }
    ],
    "صدوق اشکذر": [
      {
        "آدرس": "يزد - اشکذر - خيابان امام خميني",
        "تلفن": "32726380",
        "نام مرکز": "داروخانه دكتر سميه انتظاري- اشكذر آنلاين",
        "نوع تخصص": "داروخانه",
        "کد رایانه": 23619
      }
    ],
    "مهريز": [
      {
        "آدرس": "مهريز- خيابان هفتم تير -ميدان پرستار",
        "تلفن": "32532412",
        "نام مرکز": "آزمايشگاه وستا - آنلاين",
        "نوع تخصص": "آزمايشگاه",
        "کد رایانه": 20564
      },
      {
        "آدرس": "مهريز",
        "تلفن": "35223002",
        "نام مرکز": "بيمارستان فاطمه الزهرا_مهريز-آنلاين",
        "نوع تخصص": "بستري",
        "کد رایانه": 3569
      },
      {
        "آدرس": "مهريز - روبروي اورژانس بيمارستان",
        "تلفن": "32528810",
        "نام مرکز": "داروخانه  رضائي ( سميه رضائي ) - يزد آنلاين",
        "نوع تخصص": "داروخانه",
        "کد رایانه": 10221
      },
      {
        "آدرس": "مهريز - ميدان پرستار جنب بيمارستان فاطمه الزهرا",
        "نام مرکز": "داروخانه دكتر طباطبائي ( آقاي سيد ميثم طباطبائي ) - يزدآنلاين",
        "نوع تخصص": "داروخانه",
        "کد رایانه": 26174
      },
      {
        "آدرس": "شهرک امام خميني خيابان مطهري جنوبي جنب اورژانس",
        "تلفن": "32525759",
        "نام مرکز": "داروخانه دكتر معزالدين حيدري",
        "نوع تخصص": "داروخانه",
        "کد رایانه": 29328
      },
      {
        "آدرس": "مهريز - ميدان پرستار - روبروي بيمارستان فاطمه الزهرا",
        "تلفن": "32530399",
        "نام مرکز": "داروخانه دكتر نسرين زارع بيدكي - يزد آنلاين",
        "نوع تخصص": "داروخانه",
        "کد رایانه": 27428
      },
      {
        "آدرس": "مهريز - بلوار 7 تير - انتهاي بلوار",
        "تلفن": "35223002",
        "نام مرکز": "درمانگاه فاطمه الزهرا - مهريز",
        "نوع تخصص": "کلينيک/درمانگاه",
        "کد رایانه": 25309
      },
      {
        "آدرس": "مهريز - بلوار هفتم تير - نرسيده به ميدان پرستار - روبروي بانک تجارت",
        "تلفن": "32521448",
        "نام مرکز": "عينك فروشي روشنا - ( فرزانه فراحت ) - يزد",
        "نوع تخصص": "اپتومتريست -عينک",
        "کد رایانه": 14940
      }
    ],
    "ميبد": [
      {
        "آدرس": "ميبد-خيابان امام  جنب درمانگاه امين آزمايشگاه محک",
        "تلفن": "32301616",
        "نام مرکز": "آزمايشگاه محك (فهيمه خادم الحسيني) ميبد - آنلاين",
        "نوع تخصص": "آزمايشگاه تشخيص طبي",
        "کد رایانه": 20523
      },
      {
        "آدرس": "ميبد -",
        "تلفن": "32321757",
        "نام مرکز": "آزمايشگاه ميبد شفا (دكتر محمد افخمي عقدا ) - ميبدآنلاين",
        "نوع تخصص": "آزمايشگاه",
        "کد رایانه": 10152
      },
      {
        "آدرس": "فيروزآباد خيابان سلمان فارسي نبش کوچه پارسا 16",
        "تلفن": "32327502",
        "نام مرکز": "آزمايشگاه نويان پژوهان(آنلاين)",
        "نوع تخصص": "آزمايشگاه تشخيصي پزشکي",
        "کد رایانه": 29160
      },
      {
        "آدرس": "ميبد - فلکه شهرداري",
        "تلفن": "32351200",
        "نام مرکز": "بيمارستان امام جعفرصادق_ميبد-آنلاين",
        "نوع تخصص": "بستري",
        "کد رایانه": 3572
      },
      {
        "آدرس": "ميبد - خيابان امام- ابتداي خيابان بنياد شهيد",
        "تلفن": "32342524",
        "نام مرکز": "داروخانه پاستور ( دكتر محدثه برزگر ) - ميبد آنلاين",
        "نوع تخصص": "داروخانه",
        "کد رایانه": 23575
      },
      {
        "آدرس": "ميبد - خ امام خميني",
        "تلفن": "03535221406",
        "نام مرکز": "داروخانه شبانه روزي ابن سينا ميبد (دكتر مهدي شفيعي) - ميبد-آنلاين",
        "نوع تخصص": "داروخانه",
        "کد رایانه": 10604
      },
      {
        "آدرس": "ميبد - خيابان امام خميني - ساختمان جنب سپاه پاسدارن",
        "تلفن": "32328585",
        "نام مرکز": "درمانگاه امام حسين ( ع ) - (دكتر امامي ميبدي ) - ميبد آنلاين",
        "نوع تخصص": "کلينيک/درمانگاه",
        "کد رایانه": 23020
      },
      {
        "آدرس": "يزد - ميبد-ميدان بيت العباس- بلوار شهيد فاضلي",
        "تلفن": "32324548",
        "نام مرکز": "فيزيوتراپي امام رضا (دكتر سيدمصطفي منتظري) - ميبد-آنلاين",
        "نوع تخصص": "فيزيوتراپي",
        "کد رایانه": 21725
      },
      {
        "آدرس": "ميبد - اميرآباد - روبرو استخر مهر نبش کوچه نسترن 72",
        "تلفن": "32384151",
        "نام مرکز": "فيزيوتراپي رازي( خانم فاطمه خادم الحسيني)- ميبد آنلاين",
        "نوع تخصص": "فيزيوتراپي",
        "کد رایانه": 27675
      },
      {
        "آدرس": "ميبد ميدان بيت العباس",
        "تلفن": "32329843",
        "نام مرکز": "كلينيك فيزيوتراپي تسكين -خانم طيبه دهقاني -  آنلاين",
        "نوع تخصص": "فيزيوتراپي",
        "کد رایانه": 27112
      }
    ],
    "يزد": [
      {
        "آدرس": "يزد - بلوار طالقاني - کوچه مجاهد - جنب ساختمان پزشکان رازي",
        "تلفن": "37259091",
        "نام مرکز": "آزمايشگاه بوعلي ( دكترمحمد حسين سالاري ) - يزد آنلاين",
        "نوع تخصص": "آزمايشگاه",
        "کد رایانه": 10232
      },
      {
        "آدرس": "يزد - بلوار شهيد دشتي - روبروي بوستان ناجي",
        "تلفن": "3838099",
        "نام مرکز": "آزمايشگاه پاتوبيولوژي دكتر خبازيان - يزد-آنلاين",
        "نوع تخصص": "آزمايشگاه",
        "کد رایانه": 13210
      },
      {
        "آدرس": "يزد- خ کاشاني - کوچه زايشگاه بهمن",
        "تلفن": "36285560",
        "نام مرکز": "آزمايشگاه پاتوبيولوژي رازي ( دكترسيدمحمودقريشيان) - يزد",
        "نوع تخصص": "آزمايشگاه",
        "کد رایانه": 10230
      },
      {
        "آدرس": "يزد-بلوار دانشگاه - خيابان شهيد تندگويان",
        "تلفن": "38343535",
        "نام مرکز": "آزمايشگاه پارس ( دكتر ياسمين رازي ) - يزد",
        "نوع تخصص": "آزمايشگاه تشخيص پزشکي",
        "کد رایانه": 20341
      },
      {
        "آدرس": "يزد -بلوار طالقاني -روبروي بانک تجارت",
        "تلفن": "36272090",
        "نام مرکز": "آزمايشگاه پارس (دكترحميد جراحي )-يزدآنلاين",
        "نوع تخصص": "آزمايشگاه",
        "کد رایانه": 9937
      },
      {
        "آدرس": "يزد - ميدان مهديه - ابتداي بلوار طالقاني - کوچه اول",
        "تلفن": "36229053",
        "نام مرکز": "آزمايشگاه پاستور ( دكتر خليل ارجمندزاده ) يزد -آنلاين",
        "نوع تخصص": "آزمايشگاه",
        "کد رایانه": 10798
      },
      {
        "آدرس": "يزد- بلوار شهيد صدوقي جنوبي - حدفاصل کوچه 15و17 -کلينيک خورشيد",
        "تلفن": "37283800",
        "نام مرکز": "آزمايشگاه پرتو (خانم فاطمه مشكوه)-يزد-آنلاين",
        "نوع تخصص": "آزمايشگاه تشخيصي پزشکي",
        "کد رایانه": 21580
      },
      {
        "آدرس": "بلوار طالقاني بعد از کوچه حنا",
        "تلفن": "36265062",
        "نام مرکز": "آزمايشگاه تشخيصي آينده(آنلاين)",
        "نوع تخصص": "آزمايشگاه تشخيصي پزشکي",
        "کد رایانه": 29154
      },
      {
        "آدرس": "آزادشهر- نبش فلکه اول",
        "تلفن": "37213764",
        "نام مرکز": "آزمايشگاه تشخيصي پزشكي امام رضا (ع)(دكتر محمرضا پهلوان زاده)-آنلاين",
        "نوع تخصص": "آزمايشگاه تشخيص طبي",
        "کد رایانه": 20563
      },
      {
        "آدرس": "خيابان کاشاني کوچه حافظ",
        "تلفن": "36249991",
        "نام مرکز": "آزمايشگاه حافظ( آنلاين) يزد",
        "نوع تخصص": "آزمايشگاه تشخيصي پزشکي",
        "کد رایانه": 30469
      },
      {
        "آدرس": "يزد-صفائيه-خ تيمسار فلاحي",
        "تلفن": "38242488",
        "نام مرکز": "آزمايشگاه دنا تشخيص -يزد-آنلاين",
        "نوع تخصص": "آزمايشگاه تشخيصي پزشکي",
        "کد رایانه": 21714
      },
      {
        "آدرس": "يزد - بلوار طالقاني - روبروي بانک ملت",
        "تلفن": "37258850",
        "نام مرکز": "آزمايشگاه سينا ( دكتر محمد جواد آريا ) - يزد آنلاين",
        "نوع تخصص": "آزمايشگاه",
        "کد رایانه": 10336
      },
      {
        "آدرس": "يزد - بلوارجمهوري - روبروي بانک رفاه - جنب کوچه اورژانس بيمارستان افشار",
        "تلفن": "35250625",
        "نام مرکز": "آزمايشگاه صدرا (دكتر محمدرضا وطني باف) - يزدآنلاين",
        "نوع تخصص": "آزمايشگاه",
        "کد رایانه": 10231
      },
      {
        "آدرس": "يزد - خيابان طالقاني - کوچه 8 - شهيد زماني - انتهاي کوچه - پلاک 7",
        "تلفن": "37256458",
        "نام مرکز": "آزمايشگاه فارابي ( صائب تقي زاده ) - يزد آنلاين",
        "نوع تخصص": "آزمايشگاه تشخيصي پزشکي",
        "کد رایانه": 24422
      },
      {
        "آدرس": "يزد - صفائيه - خ تيمسار فلاحي - روبروي بازارچه اطلسي",
        "تلفن": "38351060",
        "نام مرکز": "آزمايشگاه كسري (دكتر ليلا دهقان )- يزد آنلاين",
        "نوع تخصص": "آزمايشگاه",
        "کد رایانه": 10180
      },
      {
        "آدرس": "يزد- خيابان کاشاني- بعد از ساختمان پزشکان آباديس",
        "تلفن": "38275385",
        "نام مرکز": "آزمايشگاه لقمان - يزد -آنلاين",
        "نوع تخصص": "آزمايشگاه",
        "کد رایانه": 21344
      },
      {
        "آدرس": "يزد-ميدان باهنر-",
        "تلفن": "37268373",
        "نام مرکز": "آزمايشگاه ميلاد(دكتر محمدعلي فرجام فرد)-يزدآنلاين",
        "نوع تخصص": "آزمايشگاه",
        "کد رایانه": 10117
      },
      {
        "آدرس": "يزد - ميدان مهديه - ابتداي بلوار امام جعفر صادق",
        "تلفن": "36298100",
        "نام مرکز": "آزمايشگاه نوبل (دكترمليحه زارع ) يزد-آنلاين",
        "نوع تخصص": "آزمايشگاه تشخيصي پزشکي",
        "کد رایانه": 19312
      },
      {
        "آدرس": "يزد - ابتداي بلوار منتظرقائم - کوچه شهيد نصيري ( اکبرآباد)",
        "تلفن": "36293666",
        "نام مرکز": "آزمايشگاه نور (دكتر فاطمه سررشته داريزدي ) - يزد آنلاين",
        "نوع تخصص": "آزمايشگاه",
        "کد رایانه": 10278
      },
      {
        "آدرس": "يزد - خيابان سلمان",
        "تلفن": "36262081",
        "نام مرکز": "بيمارستان   گودرز_يزد آنلاين",
        "نوع تخصص": "بستري",
        "کد رایانه": 3576
      },
      {
        "آدرس": "استان يزد ، شهرستان يزد ، بخش مرکزي ، شهر يزد، محله وحدت ، کوچه 18جمهوري[اورژانس] ، بلوار جمهوري اسلامي ، پلاک 0 ، طبقه همکف",
        "تلفن": "35255011",
        "نام مرکز": "بيمارستان افشار_يزد آنلاين",
        "نوع تخصص": "بستري ( قلب و عروق )",
        "کد رایانه": 3563
      },
      {
        "آدرس": "يزد- نبش ميدان مهديه",
        "تلفن": "36230030",
        "نام مرکز": "بيمارستان تخصصي زايمان مادر_يزد آنلاين",
        "نوع تخصص": "بستري ( بيماريهاي زنان و زايمان و نازايي )",
        "کد رایانه": 3577
      },
      {
        "آدرس": "يزد - خيابان امام",
        "تلفن": "31655380",
        "نام مرکز": "بيمارستان حضرت سيدالشهدا_يزد آنلاين",
        "نوع تخصص": "بستري ( قلب و عروق و جراحي عمومي )",
        "کد رایانه": 3575
      },
      {
        "آدرس": "يزد - ميدان شهداي محراب - ابتداي خيابان کاشاني",
        "تلفن": "38248000",
        "نام مرکز": "بيمارستان دكتر مرتاض يزد آنلاين",
        "نوع تخصص": "بستري",
        "کد رایانه": 3579
      },
      {
        "آدرس": "يزد چهاره راه معلم",
        "تلفن": "35250093",
        "نام مرکز": "بيمارستان سوانح و سوختگي_يزدآنلاين",
        "نوع تخصص": "بستري ( ترميم اسکار سوختگي )",
        "کد رایانه": 3564
      },
      {
        "آدرس": "يزد- بلوار جوان - ميدان عالم  - جنب دانشگاه آزاد اسلامي يزد",
        "تلفن": "38211091",
        "نام مرکز": "بيمارستان شاه ولي افشاريان يزد( آنلاين)",
        "نوع تخصص": "بستري ( سرطاني - شيمي درماني )",
        "کد رایانه": 3580
      },
      {
        "آدرس": "يزد",
        "نام مرکز": "بيمارستان شهداي كارگر_يزد",
        "نوع تخصص": "بستري",
        "کد رایانه": 3567
      },
      {
        "آدرس": "يزد - خيابان فرخي",
        "تلفن": "36260001",
        "نام مرکز": "بيمارستان شهيد  رهنمون_يزد",
        "نوع تخصص": "بستري ( تروما )",
        "کد رایانه": 3565
      },
      {
        "آدرس": "يزد صفائيه",
        "تلفن": "38224001",
        "نام مرکز": "بيمارستان شهيد  صدوقي_يزد",
        "نوع تخصص": "بيمارستان عمومي - طرف قرارداد با بيمه گر پايه",
        "کد رایانه": 3566
      },
      {
        "آدرس": "سه راه شهنه",
        "تلفن": "36261566",
        "نام مرکز": "تصوير بداي درمانگاه فرهنگيان(آنلاين) -يزد",
        "نوع تخصص": "مركز تصوير برداري",
        "کد رایانه": 30475
      },
      {
        "آدرس": "ميدان کاج",
        "تلفن": "38227000",
        "نام مرکز": "تصوير برداري درمانگاه كوثر شفاء (آنلاين) -يزد",
        "نوع تخصص": "مركز تصوير برداري",
        "کد رایانه": 30468
      },
      {
        "آدرس": "بلوار صدوقي",
        "تلفن": "31242241",
        "نام مرکز": "تصويربرداري امام جعفر صادق (آنلاين) -يزد",
        "نوع تخصص": "مركز تصوير برداري",
        "کد رایانه": 30477
      },
      {
        "آدرس": "يزد-آزادشهر - فلکه چهارم - بلوار گلستان شرقي - کوچه 25",
        "تلفن": "37220086",
        "نام مرکز": "خانم دكتر فروغ مهتاب - يزد آنلاين",
        "نوع تخصص": "پزشک عمومي",
        "کد رایانه": 15391
      },
      {
        "آدرس": "يزد - خ کاشاني - روبروي بانک کشاورزي",
        "تلفن": "36264288",
        "نام مرکز": "داروخانه جمعيت هلال احمر - يزد آنلاين",
        "نوع تخصص": "داروخانه",
        "کد رایانه": 10667
      },
      {
        "آدرس": "يزد - ميدان مهديه - بلوارشهيد بهشتي - روبروي بنياد شهيد",
        "تلفن": "37242325",
        "نام مرکز": "داروخانه دكتر ابريشم(دكتر سيده نگين ابريشم ) - يزد آنلاين",
        "نوع تخصص": "داروخانه",
        "کد رایانه": 23900
      },
      {
        "آدرس": "يزد - صفائيه - ميدان جانباز",
        "تلفن": "38240703",
        "نام مرکز": "داروخانه دكتر پور شفيعي ( محمدرضا پور شفيعي ) - يزدآنلاين",
        "نوع تخصص": "داروخانه",
        "کد رایانه": 11881
      },
      {
        "آدرس": "يزد - ميدان نماز",
        "تلفن": "36292005",
        "نام مرکز": "داروخانه دكتر جامه داران ( آقاي احسان جامه داران ) - يزدآنلاين",
        "نوع تخصص": "داروخانه",
        "کد رایانه": 26173
      },
      {
        "آدرس": "يزد - ميدان باغ ملي - ابتداي مطهري",
        "تلفن": "36268004",
        "نام مرکز": "داروخانه دكتر حكيمي ( مصطفي حكيمي ) - يزدآنلاين",
        "نوع تخصص": "داروخانه",
        "کد رایانه": 15250
      },
      {
        "آدرس": "يزد-بلوارشهيد صدوقي-جنب مخابرات",
        "تلفن": "37243424",
        "نام مرکز": "داروخانه دكتر دهقاني- يزد آنلاين",
        "نوع تخصص": "داروخانه",
        "کد رایانه": 9951
      },
      {
        "آدرس": "صفائيه - بعداز ميدان شهداي محراب - خيابان 15 خرداد -انستيتو سلامتي صبا",
        "تلفن": "38278980",
        "نام مرکز": "داروخانه دكتر رضا شفيعي - يزد-آنلاين",
        "نوع تخصص": "داروخانه",
        "کد رایانه": 10039
      },
      {
        "آدرس": "يزد - بلوار شهيد دشتي - بين کوچه 15 و 17 -",
        "تلفن": "38222488",
        "نام مرکز": "داروخانه دكتر زارع زرديني ( دكتر محمد مهدي زارع زرديني ) - يزدآنلاين",
        "نوع تخصص": "داروخانه",
        "کد رایانه": 23569
      },
      {
        "آدرس": "يزد - خ معلم - درمانگاه فرهنگيان",
        "تلفن": "36264402",
        "نام مرکز": "داروخانه دكتر سخنور ( دكتر مريم حباب ) - يزد-آنلاين",
        "نوع تخصص": "داروخانه",
        "کد رایانه": 10286
      },
      {
        "آدرس": "يزد -بلوار شهيد صدوقي",
        "تلفن": "37265010",
        "نام مرکز": "داروخانه دكتر سعيد غلامي-يزد- آنلاين",
        "نوع تخصص": "داروخانه",
        "کد رایانه": 9940
      },
      {
        "آدرس": "يزد امام شهر بلوار کارگر جنوبي ميدان شهيد حسيني زاده",
        "نام مرکز": "داروخانه دكتر سعيده ميروكيلي",
        "نوع تخصص": "داروخانه",
        "کد رایانه": 30388
      },
      {
        "آدرس": "يزد - بلوارمدرس - اکرميه - خيابان ابوالفضل",
        "تلفن": "38343132",
        "نام مرکز": "داروخانه دكتر سيد سينا منتخب - يزد آنلاين",
        "نوع تخصص": "داروخانه",
        "کد رایانه": 27430
      },
      {
        "آدرس": "يزد - بلوار شهيد صدوقي - کوچه تالار هنر - جنب مرکز ديابت",
        "تلفن": "32422510",
        "نام مرکز": "داروخانه دكتر سيف الديني ( محمدرضا سيف الديني ) - يزد آنلاين",
        "نوع تخصص": "داروخانه",
        "کد رایانه": 10373
      },
      {
        "آدرس": "يزد - بلوار جمهوري - جنب بيمارستان افشار",
        "تلفن": "35303092",
        "نام مرکز": "داروخانه دكتر عابدي (دكتر حميده عابدي اردكاني ) يزد-آنلاين",
        "نوع تخصص": "داروخانه",
        "کد رایانه": 27502
      },
      {
        "آدرس": "يزد - آزادشهر - خيابان آزادي - بعد از کوچه شهيد دهقاني",
        "تلفن": "35278610",
        "نام مرکز": "داروخانه دكتر علي شجاع الديني - يزد آنلاين",
        "نوع تخصص": "داروخانه",
        "کد رایانه": 11538
      },
      {
        "آدرس": "يزد - بلوار شهيد بهشتي. نرسيده به ميدان مهديه. نبش کوچه 17",
        "تلفن": "38275441",
        "نام مرکز": "داروخانه دكتر كلانتر ( هستي سادات كلانتر) - يزد آنلاين",
        "نوع تخصص": "داروخانه",
        "کد رایانه": 23576
      },
      {
        "آدرس": "خيابان مطهري حد فاصل چهارراه فرهنگيان و سه راه شحنه",
        "تلفن": "37285001",
        "نام مرکز": "داروخانه دكتر نبي ميبدي",
        "نوع تخصص": "داروخانه",
        "کد رایانه": 29806
      },
      {
        "آدرس": "يزد-بلوارجمهوري اسلامي",
        "تلفن": "37248350",
        "نام مرکز": "داروخانه دكترسراياني (دكترعباس سراياني) -يزدآنلاين مخابرات",
        "نوع تخصص": "داروخانه",
        "کد رایانه": 10121
      },
      {
        "آدرس": "خيابان امام - سه راه فهادان",
        "تلفن": "36201488",
        "نام مرکز": "داروخانه شبانه روزي دكتر اسماعيل ملانوري شمسي - يزدآنلاين",
        "نوع تخصص": "داروخانه",
        "کد رایانه": 10038
      },
      {
        "آدرس": "يزد- بلوار منتظر قائم - نبش ميدان مهديه",
        "تلفن": "36268854",
        "نام مرکز": "داروخانه شبانه روزي دكتر امامزاده يزدي ( دكتر سيدمحمد امامزاده يزدي ) - يزد آنلاين",
        "نوع تخصص": "داروخانه شبانه روزي",
        "کد رایانه": 10283
      },
      {
        "آدرس": "يزد-خ کاشاني-بعد ازمسجد اتابکي",
        "تلفن": "38247070",
        "نام مرکز": "داروخانه شبانه روزي دكتر رئيسيان-يزد- آنلاين",
        "نوع تخصص": "داروخانه",
        "کد رایانه": 9945
      },
      {
        "آدرس": "بلوار22بهمن- جنب فروشگاه چرخ گردون",
        "تلفن": "37261660",
        "نام مرکز": "داروخانه شبانه روزي دكترسيداحمدموسوي پور - يزد(آنلاين)",
        "نوع تخصص": "داروخانه",
        "کد رایانه": 10034
      },
      {
        "آدرس": "يزد - خيابان فرخي - جنب بيمارستان رهنمون",
        "تلفن": "36266900",
        "نام مرکز": "داروخانه شهيد چمران- يزد آنلاين -",
        "نوع تخصص": "داروخانه شبانه روزي",
        "کد رایانه": 11516
      },
      {
        "آدرس": "يزد - چهارراه مهديه - داخل کوچه بيمارستان مادر",
        "تلفن": "36241711",
        "نام مرکز": "دكتر جلال سعادت خواه - يزد آنلاين",
        "نوع تخصص": "فيزيوتراپي",
        "کد رایانه": 10868
      },
      {
        "آدرس": "يزد - صفائيه - بلوار شهيد قندي - کوچه 15  عدالت - پلاک 24",
        "تلفن": "38247274",
        "نام مرکز": "دكتر حسين خوان پايه - يزدآنلاين",
        "نوع تخصص": "پزشک عمومي",
        "کد رایانه": 10635
      },
      {
        "آدرس": "ابرکوه_خ شهيد صدوقي",
        "تلفن": "03532824416",
        "نام مرکز": "دكتر عباس قيومي - ابركوه آنلاين",
        "نوع تخصص": "پزشک عمومي",
        "کد رایانه": 10411
      },
      {
        "آدرس": "يزد - پمپ بنزين سيلو - بلوار امير کبير -بعد از نمايندگي سايپا",
        "تلفن": "38217806",
        "نام مرکز": "دكتر علي محمد جبروتي - يزد",
        "نوع تخصص": "پزشک عمومي",
        "کد رایانه": 10182
      },
      {
        "آدرس": "هرات_جنب اداره برق",
        "تلفن": "03532573020",
        "نام مرکز": "دكتر مجيد محمودي ميمند- يزد",
        "نوع تخصص": "پزشک عمومي",
        "کد رایانه": 10408
      },
      {
        "آدرس": "بلوار صدوقي",
        "تلفن": "31242241",
        "نام مرکز": "دندانپزشكي درمانگاه امام جعفر صادق (ع)",
        "نوع تخصص": "دندانپزشک- عمومي",
        "کد رایانه": 30482
      },
      {
        "آدرس": "چهار راه ، شهنه",
        "تلفن": "36271009",
        "نام مرکز": "دندانپزشكي درمانگاه فرهنگيان (آنلاين) - يزد",
        "نوع تخصص": "دندانپزشک- عمومي",
        "کد رایانه": 30479
      },
      {
        "آدرس": "يزد - صفائيه - نرسيده به تالار فرهنگيان و عدالت 10",
        "تلفن": "35283330",
        "نام مرکز": "دندانپزشكي سامان ( دكتر ياسمن مدرس سبزواري )  - يزد آنلاين",
        "نوع تخصص": "دندانپزشک- عمومي",
        "کد رایانه": 27114
      },
      {
        "آدرس": "يزد - خيابان کاشاني - جنب پمپ بنزن",
        "تلفن": "36285052",
        "نام مرکز": "شركت تعاوني راهبرد نوين سلامت دي يزد- آنلاين",
        "نوع تخصص": "آزمايشگاه",
        "کد رایانه": 10228
      },
      {
        "آدرس": "يزد - خيابان دهم فروردين - انتهاي کوچه روشن",
        "تلفن": "36263802",
        "نام مرکز": "عينك بي نظير ( آقاي سيد كاظم رقم خوان )- يزد آنلاين",
        "نوع تخصص": "عينک فروشي/ عينک سازي",
        "کد رایانه": 13824
      },
      {
        "آدرس": "بلوار طالقاني روبه رو بانک تجارت",
        "نام مرکز": "عينك فروشي رادين تحت نظر اپتومتريست آقاي مهدي دهقان بنادكي",
        "نوع تخصص": "عينک فروشي/ عينک سازي",
        "کد رایانه": 27685
      },
      {
        "آدرس": "يزد - بلوارطالقاني - کوچه شهيد منتظري - جنب بانک تجارت",
        "تلفن": "37251736",
        "نام مرکز": "عينك فروشي سميه السادات علوي دانا -يزد آنلاين",
        "نوع تخصص": "عينک فروشي/ عينک سازي",
        "کد رایانه": 27933
      },
      {
        "آدرس": "خيابان امام  روبرو درمانگاه سيدالشهدا",
        "تلفن": "36215966",
        "نام مرکز": "عينك مهران(آنلاين)-يزد",
        "نوع تخصص": "عينک فروشي/ عينک سازي",
        "کد رایانه": 30473
      },
      {
        "آدرس": "يزد - بلوار طالقاني - جنب بانک صادرات",
        "تلفن": "37253262",
        "نام مرکز": "عينك نگين ( محمد رضا هادي زاده) - يزدآنلاين",
        "نوع تخصص": "عينک فروشي/ عينک سازي",
        "کد رایانه": 10310
      },
      {
        "آدرس": "يزد- بلوار صدوقي - روبرو بهداري سپاه",
        "تلفن": "37251056",
        "نام مرکز": "فيزيوتراپي شفا - كاظم پهلوان فلاحي - يزد آنلاين",
        "نوع تخصص": "فيزيوتراپي",
        "کد رایانه": 11085
      },
      {
        "آدرس": "صفاييه-بلوار دانشگاه-فرساد11",
        "تلفن": "38253300",
        "نام مرکز": "كلينيك دندانپزشكي آراد(دكتر سيدروح الله هاشمي نژاد)-يزد-آنلاين",
        "نوع تخصص": "دندانپزشک عمومي و متخصص",
        "کد رایانه": 10114
      },
      {
        "آدرس": "يزد - بلوارجمهوري - چهار راه محمودآباد- خانه کارگر",
        "تلفن": "35283330",
        "نام مرکز": "كلينيك دندانپزشكي بهشتي (دكتر رومينا سيدمروستي) - يزد آفلاين",
        "نوع تخصص": "دندانپزشکي",
        "کد رایانه": 13211
      },
      {
        "آدرس": "يزد - خيابان چمران- کوچه جنب بانک سپه - پلاک 16",
        "تلفن": "36237575",
        "نام مرکز": "كلينيك فيزيوتراپي خاتم الانبيا ( كاظم كريمي زارچي ) - يزد آنلاين",
        "نوع تخصص": "فيزيوتراپي",
        "کد رایانه": 13850
      },
      {
        "آدرس": "خيابان طالقاني روبرو بيمه ايران",
        "تلفن": "36268156",
        "نام مرکز": "لامارك",
        "نوع تخصص": "آزمايشگاه تشخيصي پزشکي",
        "کد رایانه": 30179
      },
      {
        "آدرس": "بلوار شهيد صدوقي - کوچه خرمشاد",
        "تلفن": "31242241-37251077",
        "نام مرکز": "مجتمع درمانگاهي امام جعفرصادق ( دكتر فاطمه همايون) -يزد-آنلاين",
        "نوع تخصص": "درمانگاه",
        "کد رایانه": 14521
      },
      {
        "آدرس": "استان يزد - شهر يزد",
        "تلفن": "36273945",
        "نام مرکز": "مركز تصويربرداري فك و صورت پرتو(آنلاين)",
        "نوع تخصص": "راديولوژي ( تصوير برداري )",
        "کد رایانه": 29068
      },
      {
        "آدرس": "يزد - بلوار22 بهمن - کوچه جنب بانک صادرات - نبش کوچه شهيد لوک زاده",
        "تلفن": "37246365",
        "نام مرکز": "مركز توانبخشي پاك مهر - دكتر سيده سميه شيرمحمدي - يزد-آنلاين",
        "نوع تخصص": "فيزيوتراپي",
        "کد رایانه": 14855
      },
      {
        "آدرس": "خيابان کاشاني بعد از سه راه شهيد چمران",
        "تلفن": "36280118",
        "نام مرکز": "مركز جامع توانبخشي شهداي امدادگر هلال احمر",
        "نوع تخصص": "کلينيک/درمانگاه",
        "کد رایانه": 29731
      },
      {
        "آدرس": "52 متر امام شهر",
        "تلفن": "035-3379",
        "نام مرکز": "مركز جذاحي فاطمه الزهرا(آنلاين)- يزد",
        "نوع تخصص": "مرکز جراحي محدود و چشم پزشکي",
        "کد رایانه": 30471
      },
      {
        "آدرس": "يزد- خيابان معلم - خيابان مطهري",
        "تلفن": "36271008",
        "نام مرکز": "مركزبهداشتي درماني فرهنگيان - يزد آنلاين",
        "نوع تخصص": "کلينيک/درمانگاه",
        "کد رایانه": 10948
      },
      {
        "آدرس": "يزد - بلوار پاکنژاد",
        "تلفن": "37248105",
        "نام مرکز": "مركزجراحي محدود دكتر موسوي بيوكي  - يزدآنلاين",
        "نوع تخصص": "مرکز جراحي محدود و چشم پزشکي",
        "کد رایانه": 3581
      },
      {
        "آدرس": "يزد - صفائيه - فلکه کاج",
        "تلفن": "38227000",
        "نام مرکز": "مركزدرماني كوثر شفا_يزد آنلاين",
        "نوع تخصص": "کلينيک/درمانگاه",
        "کد رایانه": 3582
      },
      {
        "آدرس": "يزد -ميدان آيت الله خاتمي -خيابان خرمشهر",
        "تلفن": "36247977",
        "نام مرکز": "مطب دكتر اسماعيل خواجه زاده-يزد -آنلاين",
        "نوع تخصص": "پزشک عمومي",
        "کد رایانه": 11819
      },
      {
        "آدرس": "خيابان کاشاني روبرو پار هفت تير ساختمان کيميا",
        "تلفن": "38363415",
        "نام مرکز": "مطب دكتر محمدعلي طيب زاده (آنلاين)يزد",
        "نوع تخصص": "متخصص بيماري هاي عفوني",
        "کد رایانه": 30590
      },
      {
        "آدرس": "يزد - اطلسي - بلوار دانشگاه - خيابان شاهد- شاهد 6",
        "تلفن": "38265332",
        "نام مرکز": "موسسه فيزيوتراپي مهدي قاسمي - يزد آنلاين",
        "نوع تخصص": "فيزيوتراپي",
        "کد رایانه": 26183
      },
      {
        "آدرس": "ميدان آزادي بلوار طالقاني نرسيد به مسجد مهدي پلاک 226",
        "تلفن": "03537286628",
        "نام مرکز": "نفيسه كلانتري (آنلاين) - فتوح",
        "نوع تخصص": "متخصص بيماريهاي داخلي قلب و عروق",
        "کد رایانه": 28177
      }
    ]
  }
}